{"basics":{"name":"Binh Huynh","label":"","profile":"https:\/\/www.linkedin.com\/in\/binh-huynh-94555794\/"},"work":[{"company":"Media Ventures Vietnam Group&#44; Ho Chi Minh City","summary":"HR Executive","desc":"","startDate":"Jun 2016 ","endDate":" Present "},{"company":"Harvey Nash Vietnam&#44; Vietnam","summary":"Research Analyst","desc":"- Look for the most senior positions in abundant fields such as Sales and Marketing, Human Resources, Finance, Education, Fundraising...\n- Main Markets: UK, APAC\n- Use job boards, special platforms and internal tools to look for potential candidates at the most senior level.\n- Use internal tool to clean, enrich, input, update the data related to candidates, clients, companies information.\n- Other works as assigned by PM\/TL.","startDate":"May 2015 ","endDate":"Jun 2016"},{"company":"Harvey Nash","summary":"Data Processing Operator","desc":"","startDate":"Mar 2014 ","endDate":"May 2015"}],"education":[{"institution":"Van Hien University","studyType":"Bachelor\u2019s Degree&#44; Business Administration and Management","startDate":"2008 ","endDate":"2012"},{"institution":"Nguyen Cong Tru High School","studyType":"High School","startDate":"2005 ","endDate":"2008"}],"skills":["Management","Recruiting","Marketing Strategy","Human Resources","Team Management","Training","Contract Recruitment","Team Leadership","Negotiation","Sourcing","Leadership"],"category":{"Technology":{"point":1,"skills":[[{"work_pos":{"company":"Harvey Nash","summary":"Data Processing Operator"},"point":1}]]},"Law\/Tax":{"point":2,"skills":[[{"work_pos":{"company":"Media Ventures Vietnam Group, Ho Chi Minh City","summary":"HR Executive"},"point":3}],{"skill":"Recruiting","point":2},{"skill":"Training","point":2},{"skill":"Contract Recruitment","point":2}]},"Careers":{"point":2,"skills":[[{"work_pos":{"company":"Media Ventures Vietnam Group, Ho Chi Minh City","summary":"HR Executive"},"point":2}],{"skill":"Training","point":2}]},"Fashion Spa":{"point":2,"skills":[[{"work_pos":{"company":"Harvey Nash Vietnam, Vietnam","summary":"Research Analyst"},"point":2}]]},"Travel Transportation":{"point":4,"skills":[[{"work_pos":{"company":"Harvey Nash Vietnam, Vietnam","summary":"Research Analyst"},"point":4}]]},"Places":{"point":4,"skills":[[{"work_pos":{"company":"Media Ventures Vietnam Group, Ho Chi Minh City","summary":"HR Executive"},"point":3}],[{"work_pos":{"company":"Media Ventures Vietnam Group, Ho Chi Minh City","summary":"HR Executive"},"point":3},{"work_pos":{"company":"Harvey Nash Vietnam, Vietnam","summary":"Research Analyst"},"point":4}]]},"Shopping":{"point":2,"skills":[[{"work_pos":{"company":"Media Ventures Vietnam Group, Ho Chi Minh City","summary":"HR Executive"},"point":3}],[{"work_pos":{"company":"Media Ventures Vietnam Group, Ho Chi Minh City","summary":"HR Executive"},"point":3},{"work_pos":{"company":"Harvey Nash Vietnam, Vietnam","summary":"Research Analyst"},"point":1}]]}}}