{"basics":{"name":"Homan hesami","label":"","profile":"https:\/\/www.linkedin.com\/in\/homan-hesami-873a407a\/"},"work":[{"company":"Ronak Lighting Industries Co&#44; Tehran","summary":"Chief Financial Officer","desc":"","startDate":"Sep 2009 ","endDate":" Present "}],"education":[],"skills":["Management","Accounting","Microsoft Office","Microsoft Excel","Financial Reporting","Financial Analysis","Managerial Finance","Strategic Planning","Financial Accounting","Finance"],"category":{"Technology":{"point":1,"skills":[{"skill":"Microsoft Office","point":1},{"skill":"Microsoft Excel","point":1}]},"Law\/Tax":{"point":3,"skills":[[{"work_pos":{"company":"Ronak Lighting Industries Co, Tehran","summary":"Chief Financial Officer"},"point":4}],{"skill":"Accounting","point":2}]},"Travel Transportation":{"point":13,"skills":[[{"work_pos":{"company":"Ronak Lighting Industries Co, Tehran","summary":"Chief Financial Officer"},"point":3}],{"skill":"Accounting","point":22}]},"Places":{"point":2,"skills":[[{"work_pos":{"company":"Ronak Lighting Industries Co, Tehran","summary":"Chief Financial Officer"},"point":2}],{"skill":"Accounting","point":2}]}}}